boms_wrapper.cp310-win_amd64.pyd
boms/__init__.py
boms/boms_wrapper.cpp
boms/indicators.hpp
boms/main.py
boms/meanshift.cpp
boms/meanshift.hpp
boms/utils_vis.py
boms-1.1.0.dist-info/LICENSE
boms-1.1.0.dist-info/METADATA
boms-1.1.0.dist-info/WHEEL
boms-1.1.0.dist-info/top_level.txt
boms-1.1.0.dist-info/RECORD
