Metadata-Version: 2.1
Name: boms
Version: 1.1.0
Summary: Cell Segmentation for Spatial Transcriptomics Data using BOMS
Author: Ocima Kamboj
Author-email: Ocima Kamboj <ocimakamboj@gmail.com>
License: Copyright (c) Ocima Kamboj
Project-URL: Homepage, https://github.com/ocimakamboj/boms
Classifier: Programming Language :: Python :: 3
Classifier: License :: OSI Approved :: MIT License
Requires-Python: >=3.9
License-File: LICENSE
Requires-Dist: numpy
Requires-Dist: mkl
Requires-Dist: mkl-service
Requires-Dist: scipy
Requires-Dist: matplotlib
Requires-Dist: scikit-learn
Provides-Extra: test
Requires-Dist: scikit-learn ; extra == 'test'
